{
  "tool_name": "list_directory_with_sizes",
  "server_name": "filesystem",
  "tool_purpose": "Get a detailed listing of all files and directories in a specified path, including sizes. Results clearly distinguish between files and directories with [FILE] and [DIR] prefixes. This tool is useful for understanding directory structure and finding specific files within a directory. Only works within allowed directories.",
  "input_schema_raw": {
    "type": "object",
    "properties": {
      "path": {
        "type": "string"
      },
      "sortBy": {
        "type": "string",
        "enum": [
          "name",
          "size"
        ]
      }
    },
    "required": [
      "path",
      "sortBy"
    ]
  },
  "arguments": [
    {
      "name": "path",
      "type": "string",
      "required": true,
      "default": null,
      "enum": null,
      "description": null,
      "items_type": null,
      "properties": null,
      "required_properties": [],
      "nullable": false,
      "format": null,
      "schema_path": "$.properties.path"
    },
    {
      "name": "sortBy",
      "type": "string",
      "required": true,
      "default": null,
      "enum": [
        "name",
        "size"
      ],
      "description": null,
      "items_type": null,
      "properties": null,
      "required_properties": [],
      "nullable": false,
      "format": null,
      "schema_path": "$.properties.sortBy"
    }
  ],
  "output_hint": null,
  "auth_or_env_notes": null,
  "usage_warnings": [],
  "doc_snippets": [
    "Get a detailed listing of all files and directories in a specified path, including sizes. Results clearly distinguish between files and directories with [FILE] and [DIR] prefixes. This tool is useful for understanding directory structure and finding specific files within a directory. Only works within allowed directories.",
    "List Directory with Sizes"
  ],
  "source_pointer": "data\\raw\\harvested_mcp_reference_servers.json#8"
}