{
  "tool_name": "list_directory_with_sizes",
  "baseline_name": "retrieved_candidates",
  "source_pointer": "data\\raw\\harvested_mcp_reference_servers.json#8",
  "valid": true,
  "issues": [],
  "semantic_hints": {},
  "method_trace": [
    {
      "selection_strategy": "candidate_retrieval_shortlist",
      "shortlist": [
        "list_directory_with_sizes",
        "list_directory",
        "get_file_info"
      ],
      "distinctive_terms": [
        "list_directory_with_sizes",
        "sizes.",
        "useful",
        "sizes"
      ]
    }
  ]
}